README.md
setup.cfg
setup.py
nimblehelper/__init__.py
nimblehelper/cache.py
nimblehelper/code.py
nimblehelper/decorators.py
nimblehelper/exceptions.py
nimblehelper/health.py
nimblehelper/helper.py
nimblehelper/settings.py
nimblehelper/testsuite.py
nimblehelper/utils.py
nimblehelper/views.py
nimblehelper.egg-info/PKG-INFO
nimblehelper.egg-info/SOURCES.txt
nimblehelper.egg-info/dependency_links.txt
nimblehelper.egg-info/not-zip-safe
nimblehelper.egg-info/requires.txt
nimblehelper.egg-info/top_level.txt