Metadata-Version: 1.0
Name: nimblehelper
Version: 0.6.41
Summary: Nimble Infrastructure Helper
Home-page: UNKNOWN
Author: Brendan Kamp
Author-email: brendan@tangentsolutions.co.za
License: MIT
Platform: UNKNOWN
